MANIFEST.in
README
README.markdown
setup.py
async/__init__.py
async/admin.py
async/api.py
async/helpers.py
async/logger.py
async/models.py
async/slumber_operations.py
async/slumber_server.py
async/stats.py
async/utils.py
async/management/__init__.py
async/management/commands/__init__.py
async/management/commands/flush_queue.py
async/management/commands/queue_health.py
async/migrations/0001_initial.py
async/migrations/__init__.py
async/south_migrations/0001_initial.py
async/south_migrations/0002_auto__add_group__add_field_job_group.py
async/south_migrations/0003_auto__add_field_job_cancelled.py
async/south_migrations/0004_auto__add_field_group_final.py
async/south_migrations/0005_indexes.py
async/south_migrations/__init__.py
async/tests/__init__.py
async/tests/test_admin.py
async/tests/test_api.py
async/tests/test_commands.py
async/tests/test_deschedule.py
async/tests/test_execute.py
async/tests/test_flush_queue.py
async/tests/test_helpers.py
async/tests/test_models.py
async/tests/test_schedule.py
async/tests/test_slumber_server.py
async/tests/test_stats.py
async/tests/test_utils.py
django_async.egg-info/PKG-INFO
django_async.egg-info/SOURCES.txt
django_async.egg-info/dependency_links.txt
django_async.egg-info/requires.txt
django_async.egg-info/top_level.txt