Metadata-Version: 1.1
Name: django-async
Version: 0.7.3
Summary: Asynchronous task execution with proper database transaction management for Django
Home-page: http://www.kirit.com/Django%20Async
Author: Kirit Saelensminde
Author-email: kirit@felspar.com
License: Boost Software License - Version 1.0 - August 17th, 2003
Keywords: django async taskqueue task queue
Platform: UNKNOWN
Classifier: Development Status :: 4 - Beta
Classifier: Framework :: Django
Classifier: Intended Audience :: Developers
Classifier: Programming Language :: Python
Classifier: Topic :: Software Development :: Libraries :: Python Modules
Classifier: License :: OSI Approved
